LICENCE.txt
MANIFEST.in
README.rst
setup.cfg
setup.py
emencia_django_staticpages.egg-info/PKG-INFO
emencia_django_staticpages.egg-info/SOURCES.txt
emencia_django_staticpages.egg-info/dependency_links.txt
emencia_django_staticpages.egg-info/requires.txt
emencia_django_staticpages.egg-info/top_level.txt
emencia_django_staticpages.egg-info/zip-safe
staticpages/__init__.py
staticpages/apps.py
staticpages/exceptions.py
staticpages/loader.py
staticpages/settings.py
staticpages/views.py
staticpages/utils/__init__.py
staticpages/utils/tests.py